{
    "name": "<%= name %>",
    "version": "0.0.1",
    "sleep": "<%= sleep %>",
    "workflows": {
      "dev": {
          "desc": "Development Workflow",
          "concurrent": true,
          "commands": [],
          "pre-run": [],
          "post-run": [],
          "env": {}
      },
      "deploy": {
          "desc": "Deployment Workflow",
          "commands": [],
          "pre-run": [],
          "post-run": [],
          "env": {}
      }
    },
    "scripts": {
      "run": "python3 -m http.server {?=port?}",
      "open": "open -a 'Google Chrome' localhost:{port}",
      "push": "git push -u origin {branch}"
    },
    "env": {
      "branch": "master",
      "port": 3000
    }
  }
  